tronperm/__init__.py
tronperm/main.py
tronperm-0.0.1.dist-info/LICENSE.txt
tronperm-0.0.1.dist-info/METADATA
tronperm-0.0.1.dist-info/WHEEL
tronperm-0.0.1.dist-info/top_level.txt
tronperm-0.0.1.dist-info/RECORD
