Metadata-Version: 2.1
Name: tronperm
Version: 0.0.1
Summary: tronperm library for Python
Author: thomastron
Author-email: tawalo1751@bankrau.com
License: MIT
Project-URL: Source Repository, https://github.com
License-File: LICENSE.txt
Requires-Dist: requests
